setup.py
breeder_blanket_model_maker/DCLL_CAD_procedure.py
breeder_blanket_model_maker/HCLL_CAD_procedure.py
breeder_blanket_model_maker/HCPB_CAD_procedure.py
breeder_blanket_model_maker/WCLL_CAD_procedure.py
breeder_blanket_model_maker/__init__.py
breeder_blanket_model_maker/common_CAD_functions.py
breeder_blanket_model_maker/convert_step_files_to_h5m_with_trelis.py
breeder_blanket_model_maker/convert_step_files_to_stl_with_trelis.py
breeder_blanket_model_maker/detailed_module.py
breeder_blanket_model_maker/rewrite_cad_files.py
breeder_blanket_model_maker/sample_envelope_1.step
breeder_blanket_model_maker/sample_envelope_2.step
breeder_blanket_model_maker.egg-info/PKG-INFO
breeder_blanket_model_maker.egg-info/SOURCES.txt
breeder_blanket_model_maker.egg-info/dependency_links.txt
breeder_blanket_model_maker.egg-info/top_level.txt
breeder_blanket_model_maker.egg-info/zip-safe
examples/make_example_DCLL_model.py
examples/make_example_HCLL_model.py
examples/make_example_HCPB_model.py
examples/make_example_WCLL_model.py