Metadata-Version: 1.0
Name: breeder-blanket-model-maker
Version: 0.3
Summary: Input blanket envelopes and retrive detailed blanket geometry
Home-page: https://github.com/ukaea/breeder_blanket_model_maker
Author: Jonathan Shimwell
Author-email: jonathan.shimwell@ukaea.uk
License: Apache 2.0
Platform: UNKNOWN
